rememberer/__init__.py
rememberer/rememberer.py
rememberer-0.1.6.dist-info/LICENSE
rememberer-0.1.6.dist-info/METADATA
rememberer-0.1.6.dist-info/WHEEL
rememberer-0.1.6.dist-info/top_level.txt
rememberer-0.1.6.dist-info/RECORD
