Metadata-Version: 2.1
Name: rememberer
Version: 0.1.6
Summary: Rememberer is a tool to help your functions remember their previous results.
Home-page: https://github.com/ChamRun/rememberer
Author: ChamRun
Author-email: chrm@aut.ac.ir
License: MIT
Project-URL: Organization, https://chamrun.github.io/
Keywords: pickle,cache
Requires-Python: >=3.5
License-File: LICENSE
Requires-Dist: pickle5
